remoteshell_mcp/__init__.py
remoteshell_mcp/command_validator.py
remoteshell_mcp/connection_manager.py
remoteshell_mcp/host_store.py
remoteshell_mcp/server.py
remoteshell_mcp/ssh_client.py
remoteshell_mcp-1.1.1.dist-info/METADATA
remoteshell_mcp-1.1.1.dist-info/WHEEL
remoteshell_mcp-1.1.1.dist-info/entry_points.txt
remoteshell_mcp-1.1.1.dist-info/licenses/LICENSE
remoteshell_mcp-1.1.1.dist-info/RECORD
