Metadata-Version: 2.4
Name: remoteshell-mcp
Version: 1.1.1
Summary: MCP server for managing SSH connections and executing remote commands
Project-URL: Homepage, https://github.com/chouzz/remoteShell-mcp
Project-URL: Repository, https://github.com/chouzz/remoteShell-mcp
Project-URL: Issues, https://github.com/chouzz/remoteShell-mcp/issues
Project-URL: Changelog, https://github.com/chouzz/remoteShell-mcp/blob/main/CHANGELOG.md
Author-email: chouzz <zhouhua258@outlook.com>
License: MIT
License-File: LICENSE
Keywords: ai,claude,cursor,fastmcp,mcp,model-context-protocol,paramiko,remote,shell,ssh
Classifier: Development Status :: 4 - Beta
Classifier: Intended Audience :: Developers
Classifier: License :: OSI Approved :: MIT License
Classifier: Programming Language :: Python :: 3
Classifier: Programming Language :: Python :: 3.11
Classifier: Programming Language :: Python :: 3.12
Classifier: Topic :: Software Development :: Libraries :: Python Modules
Classifier: Topic :: System :: Networking
Classifier: Topic :: System :: Systems Administration
Requires-Python: >=3.11
Requires-Dist: fastmcp>=2.0.0
Requires-Dist: paramiko>=3.4.0
